work1/logic1.vhdl
-- Simple Combinatorial Circuit for Lab 1
-- AIT EV Digital Circuit 2 (2025)
-- Write your code below the comment at Line 16.

library IEEE;
use IEEE.std_logic_1164.ALL;

entity logic1 is
    port ( L, M, N : in  std_ulogic;
           X       : out std_ulogic);
end logic1;

architecture RTL of logic1 is
    signal T1, T2 : std_ulogic;
begin
    -- write your code here
    T1 <= L and M;
    T2 <= not N and M and not L;
    X <= T1 or T2;
end RTL;

work1/logic1_test.vhdl
-- Testbench of Simple Combinatorial Circuit for Lab 1
-- AIT EV Digital Circuit 2 (2025)
-- Do not edit this file

library IEEE;
use IEEE.std_logic_1164.ALL;
use std.env.ALL;

entity logic1_tb is
end logic1_tb;

architecture sim of logic1_tb is
component logic1 is
    port ( L, M, N : in  std_ulogic;
           X       : out std_ulogic);
end component;
signal L, M, N, X : std_ulogic;

begin
    L1 : logic1 port map ( L, M, N, X );

    process begin
        L <= '0'; M <= '0'; N <= '0'; wait for 50 ns;
        L <= '0'; M <= '0'; N <= '1'; wait for 50 ns;
        L <= '0'; M <= '1'; N <= '0'; wait for 50 ns;
        L <= '0'; M <= '1'; N <= '1'; wait for 50 ns;
        L <= '1'; M <= '0'; N <= '0'; wait for 50 ns;
        L <= '1'; M <= '0'; N <= '1'; wait for 50 ns;
        L <= '1'; M <= '1'; N <= '0'; wait for 50 ns;
        L <= '1'; M <= '1'; N <= '1'; wait for 49 ns;
        L <= '0'; M <= '0'; N <= '0'; wait for 1 ns;
        finish;
    end process;
end sim;

logic1_test.vcd
$date
  Fri Sep 26 11:01:57 2025
$end
$version
  GHDL v0
$end
$timescale
  1 fs
$end
$scope module standard $end
$upscope $end
$scope module textio $end
$upscope $end
$scope module std_logic_1164 $end
$upscope $end
$scope module env $end
$upscope $end
$scope module logic1_tb $end
$var reg 1 ! l $end
$var reg 1 " m $end
$var reg 1 # n $end
$var reg 1 $ x $end
$scope module l1 $end
$var reg 1 % l $end
$var reg 1 & m $end
$var reg 1 ' n $end
$var reg 1 ( x $end
$var reg 1 ) t1 $end
$var reg 1 * t2 $end
$upscope $end
$upscope $end
$enddefinitions $end
#0
0!
0"
0#
0$
0%
0&
0'
0(
0)
0*
#50000000
1#
1'
#100000000
1"
0#
1$
1&
0'
1(
1*
#150000000
1#
0$
1'
0(
0*
#200000000
1!
0"
0#
1%
0&
0'
#250000000
1#
1'
#300000000
1"
0#
1$
1&
0'
1(
1)
#350000000
1#
1'
#399000000
0!
0"
0#
0$
0%
0&
0'
0(
0)
