sat_counter.vhdl
-- 2-bit Saturating Counter for Lab 5
-- AIT EV Digital Circuit 2 (2025)
-- Add your code in the commented region.

library IEEE;
use IEEE.std_logic_1164.ALL;
use IEEE.numeric_std_unsigned.ALL;

entity sat_counter is
    port ( CLK, RST, A : in  std_ulogic;
           Y           : out std_ulogic);
end sat_counter;

-- 注意: 型や内部信号を宣言したあと，begin を書くのを忘れないように！

architecture RTL of sat_counter is
-- write your core here --
    type STATE_TYPE is (Q0, Q1, Q2, Q3);
    signal STATE, NEXT_STATE : STATE_TYPE;

begin
    process (all) begin
        NEXT_STATE <= STATE;
        Y          <= '0';
        if STATE = Q0 then
            if A = '1' then
                NEXT_STATE <= Q1;
            end if;
        elsif STATE = Q1 then
            if A = '1' then
                NEXT_STATE <= Q2;
            else
                NEXT_STATE <= Q0;
            end if;
        elsif STATE = Q2 then
            Y <= '1';
            if A = '1' then
                NEXT_STATE <= Q3;
            else
                NEXT_STATE <= Q1;
            end if;
        elsif STATE = Q3 then
            Y <= '1';
            if A = '0' then
                NEXT_STATE <= Q2;
            end if;
        end if;
    end process;

    process (CLK) begin
        if rising_edge(CLK) then
            if RST = '1' then
                STATE <= Q1;
            else
                STATE <= NEXT_STATE;
            end if;
        end if;
    end process;
--   end of your code   --
end RTL;

sat_counter_test.vhdl
-- Testbench of 2-bit Saturating Counter for Lab 5
-- AIT EV Digital Circuit 2 (2025)
-- Add your code in the commented region.

library IEEE;
use IEEE.std_logic_1164.ALL;
use std.env.ALL;

entity sat_counter_test is
end sat_counter_test;

architecture sim of sat_counter_test is
component sat_counter is
    port ( CLK, RST, A : in  std_ulogic;
           Y           : out std_ulogic);
end component;

signal CLK, RST, A : std_ulogic;
signal Y           : std_ulogic;

begin
    L1 : sat_counter port map ( CLK, RST, A, Y );

    -- write your code here --
    process begin
        CLK <= '1'; wait for 50 ns;
        CLK <= '0'; wait for 50 ns;
    end process;

    process begin
        RST <= '1'; wait for 150 ns;
        RST <= '0'; wait;
    end process;

    process begin
        A <= '1'; wait for 250 ns;
        A <= '0'; wait for 200 ns;
        A <= '1'; wait for 300 ns;
        A <= '0'; wait for 100 ns;
        A <= '1'; wait for 100 ns;
        A <= '0'; wait for 200 ns;
    end process;
    --   end of your code   --

    process begin
        wait for 1200 ns;
        finish;
    end process;
end sim;

sat_counter_test.vcd
$date
  Fri Dec 12 19:27:35 2025
$end
$version
  GHDL v0
$end
$timescale
  1 fs
$end
$scope module standard $end
$upscope $end
$scope module textio $end
$upscope $end
$scope module std_logic_1164 $end
$upscope $end
$scope module env $end
$upscope $end
$scope module numeric_std_unsigned $end
$upscope $end
$scope module numeric_std $end
$upscope $end
$scope module sat_counter_test $end
$var reg 1 ! clk $end
$var reg 1 " rst $end
$var reg 1 # a $end
$var reg 1 $ y $end
$scope module l1 $end
$var reg 1 % clk $end
$var reg 1 & rst $end
$var reg 1 ' a $end
$var reg 1 ( y $end
$var string 1 ) STATE $end
$var string 1 * NEXT_STATE $end
$comment state is not handled $end
$comment next_state is not handled $end
$upscope $end
$upscope $end
$enddefinitions $end
#0
1!
1"
1#
0$
1%
1&
1'
0(
sQ0 )
sQ1 *
#50000000
0!
0%
#100000000
1!
1%
sQ1 )
sQ2 *
#150000000
0!
0"
0%
0&
#200000000
1!
1$
1%
1(
sQ2 )
sQ3 *
#250000000
0!
0#
0%
0'
1(
sQ1 *
#300000000
1!
0$
1%
0(
sQ1 )
sQ0 *
#350000000
0!
0%
#400000000
1!
1%
sQ0 )
#450000000
0!
1#
0%
1'
sQ1 *
#500000000
1!
1%
sQ1 )
sQ2 *
#550000000
0!
0%
#600000000
1!
1$
1%
1(
sQ2 )
sQ3 *
#650000000
0!
0%
#700000000
1!
1%
1(
sQ3 )
#750000000
0!
0#
0%
0'
1(
sQ2 *
#800000000
1!
1%
1(
sQ2 )
sQ1 *
#850000000
0!
1#
0%
1'
1(
sQ3 *
#900000000
1!
1%
1(
sQ3 )
#950000000
0!
0#
0%
0'
1(
sQ2 *
#1000000000
1!
1%
1(
sQ2 )
sQ1 *
#1050000000
0!
0%
#1100000000
1!
0$
1%
0(
sQ1 )
sQ0 *
#1150000000
0!
1#
0%
1'
sQ2 *
