logic4.vhdl
-- Peak Detection Circuit for Lab 4
-- AIT EV Digital Circuit 2 (2025)
-- Add your code in the commented regions.

library IEEE;
use IEEE.std_logic_1164.ALL;
use IEEE.numeric_std_unsigned.ALL;

entity logic4 is
    port ( CLK, RST : in  std_ulogic;
           D        : in  std_ulogic_vector(3 downto 0);
           P        : out std_ulogic);
end logic4;

architecture RTL of logic4 is
    signal Q0, Q1, Q2 : std_ulogic_vector(3 downto 0);
begin
    -- write your code here --
    process (CLK) begin
        if rising_edge(CLK) then
            if RST = '1' then
                Q0 <= "0000";
                Q1 <= "0000";
                Q2 <= "0000";
            else
                Q2 <= Q1;
                Q1 <= Q0;
                Q0 <= D;
            end if;
        end if;
    end process;

    P <= '1' when (Q1 <= Q0 and Q1 <= Q2) else
        '1' when (Q1 >= Q0 and Q1 >= Q2) else
        '0';
    --   end of your code   --
end RTL;

logic4_test.vhdl
-- Testbench of Peak Detection Circuit for Lab 4
-- AIT EV Digital Circuit 2 (2025)
-- Add your code in the commented regions.

library IEEE;
use IEEE.std_logic_1164.ALL;
use IEEE.numeric_std_unsigned.ALL;
use std.env.ALL;

entity logic4_test is
end logic4_test;

architecture sim of logic4_test is
component logic4 is
    port ( CLK, RST : in  std_ulogic;
           D        : in  std_ulogic_vector(3 downto 0);
           P        : out std_ulogic);
end component;

signal CLK, RST, P : std_ulogic;
signal D           : std_ulogic_vector(3 downto 0);

begin
    L1 : logic4 port map ( CLK, RST, D, P );

    process begin
        CLK <= '1'; wait for 50 ns;
        CLK <= '0'; wait for 50 ns;
    end process;

    process begin
        RST <= '1'; wait for 110 ns;
        RST <= '0'; wait;
    end process;

    process begin
        D <= "0010"; wait for 210 ns; -- 2
        D <= "0000"; wait for 100 ns; -- 0
        D <= "0010"; wait for 100 ns; -- 2
        D <= "0101"; wait for 100 ns; -- 5
        -- write your code here --
        D <= "0010"; wait for 100 ns; -- 2
        D <= "0100"; wait for 100 ns; -- 4
        D <= "0001"; wait for 100 ns; -- 1
        D <= "0010"; wait for 100 ns; -- 2
        D <= "0001"; wait for 100 ns; -- 1
        --   end of your code   --
    end process;

    process begin
        wait for 1100 ns;
        finish;
    end process;
end sim;

work4/logic4_test.vcd
$date
  Mon Dec 01 23:47:07 2025
$end
$version
  GHDL v0
$end
$timescale
  1 fs
$end
$scope module standard $end
$upscope $end
$scope module textio $end
$upscope $end
$scope module std_logic_1164 $end
$upscope $end
$scope module numeric_std_unsigned $end
$upscope $end
$scope module numeric_std $end
$upscope $end
$scope module env $end
$upscope $end
$scope module logic4_test $end
$var reg 1 ! clk $end
$var reg 1 " rst $end
$var reg 1 # p $end
$var reg 4 $ d[3:0] $end
$scope module l1 $end
$var reg 1 % clk $end
$var reg 1 & rst $end
$var reg 4 ' d[3:0] $end
$var reg 1 ( p $end
$var reg 4 ) q0[3:0] $end
$var reg 4 * q1[3:0] $end
$var reg 4 + q2[3:0] $end
$upscope $end
$upscope $end
$enddefinitions $end
#0
1!
1"
0#
b0010 $
1%
1&
b0010 '
0(
bUUUU )
bUUUU *
bUUUU +
#50000000
0!
0%
#100000000
1!
1#
1%
1(
b0000 )
b0000 *
b0000 +
#110000000
0"
0&
#150000000
0!
0%
#200000000
1!
1%
b0010 )
#210000000
b0000 $
b0000 '
#250000000
0!
0%
#300000000
1!
1%
b0000 )
b0010 *
#310000000
b0010 $
b0010 '
#350000000
0!
0%
#400000000
1!
1%
b0010 )
b0000 *
b0010 +
#410000000
b0101 $
b0101 '
#450000000
0!
0%
#500000000
1!
0#
1%
0(
b0101 )
b0010 *
b0000 +
#510000000
b0010 $
b0010 '
#550000000
0!
0%
#600000000
1!
1#
1%
1(
b0010 )
b0101 *
b0010 +
#610000000
b0100 $
b0100 '
#650000000
0!
0%
#700000000
1!
1%
b0100 )
b0010 *
b0101 +
#710000000
b0001 $
b0001 '
#750000000
0!
0%
#800000000
1!
1%
b0001 )
b0100 *
b0010 +
#810000000
b0010 $
b0010 '
#850000000
0!
0%
#900000000
1!
1%
b0010 )
b0001 *
b0100 +
#910000000
b0001 $
b0001 '
#950000000
0!
0%
#1000000000
1!
1%
b0001 )
b0010 *
b0001 +
#1010000000
b0010 $
b0010 '
